LICENSE
MANIFEST.in
README.rst
setup.cfg
setup.py
fowler/__init__.py
fowler.corpora.egg-info/PKG-INFO
fowler.corpora.egg-info/SOURCES.txt
fowler.corpora.egg-info/dependency_links.txt
fowler.corpora.egg-info/entry_points.txt
fowler.corpora.egg-info/namespace_packages.txt
fowler.corpora.egg-info/not-zip-safe
fowler.corpora.egg-info/requires.txt
fowler.corpora.egg-info/top_level.txt
fowler/corpora/__init__.py
fowler/corpora/dispatcher.py
fowler/corpora/execnet.py
fowler/corpora/io.py
fowler/corpora/ipython.py
fowler/corpora/main.py
fowler/corpora/models.py
fowler/corpora/produce.py
fowler/corpora/util.py
fowler/corpora/bnc/__init__.py
fowler/corpora/bnc/main.py
fowler/corpora/bnc/readers.py
fowler/corpora/bnc/util.py
fowler/corpora/categorical/__init__.py
fowler/corpora/categorical/main.py
fowler/corpora/dictionary/__init__.py
fowler/corpora/dictionary/main.py
fowler/corpora/ms_paraphrase/__init__.py
fowler/corpora/ms_paraphrase/main.py
fowler/corpora/serafin03/__init__.py
fowler/corpora/serafin03/main.py
fowler/corpora/space/__init__.py
fowler/corpora/space/main.py
fowler/corpora/space/util.py
fowler/corpora/templates/classification_report.rst
fowler/corpora/word2vec/__init__.py
fowler/corpora/word2vec/main.py
fowler/corpora/wsd/__init__.py
fowler/corpora/wsd/datasets.py
fowler/corpora/wsd/experiments.py
fowler/corpora/wsd/main.py
test/test_bnc.py
test/test_brown.py
test/test_dg.py
test/test_space.py